{"i":{"KxdjKdNewu":{"id":"KxdjKdNewu","type":"interactive","subtype":"interactiveCard","setup":{"animation":{"selectedKey":"up"},"front":{"selectedKey":"fill","fill":{"opac":1,"rgb":"#cebc0b"},"txt":{"rType":"richtext","val":{"ops":[{"insert":"command-line interface (CLI)","attributes":{"color":"#ffffff","bold":true}},{"insert":"\n","attributes":{"size":"large","align":"center"}}]}},"rType":"richtext","hali":"","vali":"middle"},"back":{"selectedKey":"fill","fill":{"opac":0.15,"rgb":"#2b2b2a"},"txt":{"rType":"richtext","val":{"ops":[{"insert":"A text-based user interface that allows a user to interact with a computer in various ways.","attributes":{"color":"#cccccc"}},{"insert":"\n","attributes":{"align":"center"}}]}},"rType":"richtext","paddV1":0,"vali":"middle","hali":""}}},"WYjeulFWlh":{"id":"WYjeulFWlh","type":"interactive","subtype":"interactiveRichText","setup":{"frmeTp":{"selectedKey":"noneFrame"},"bg":{"fill":{"opac":0,"rgb":"#fff"}},"txt":{"rType":"richtext","val":{"ops":[{"insert":"Words to Know","attributes":{"color":"#ffffff"}},{"insert":"\n","attributes":{"size":"huge"}},{"insert":"Coding is full of jargon.","attributes":{"color":"#cebc0b"}},{"insert":"\n","attributes":{"size":"medium"}},{"insert":"\n","attributes":{"size":"small"}},{"insert":"While learning to code, you'll come across ","attributes":{"color":"#cccccc"}},{"insert":"technical terminology","attributes":{"bold":true,"color":"#cebc0b"}},{"insert":" all the time. We'll define many of the terms you'll come across in the course as we go. Here are some of the first words you'll need to know.","attributes":{"color":"#cccccc"}},{"insert":"\n"},{"insert":"\n","attributes":{"size":"small"}},{"insert":"You should also have a look at one of the most famous resources on the Internet, ","attributes":{"color":"#cccccc"}},{"insert":"the Jargon File","attributes":{"color":"#cebc0b","bold":true}},{"insert":", which is part of the New Hacker’s Dictionary. ","attributes":{"color":"#cccccc"}},{"insert":"\n","attributes":{"size":"normal"}}]}},"rType":"richtext","vali":"top","hali":"","paddV1":20,"frmeColo":{"color":{"opac":1,"rgb":"#e50a4f"}}}},"GiEO7KsLKv":{"id":"GiEO7KsLKv","type":"interactive","subtype":"interactiveCard","setup":{"animation":{"selectedKey":"up"},"front":{"selectedKey":"fill","fill":{"opac":1,"rgb":"#cebc0b"},"txt":{"rType":"richtext","val":{"ops":[{"insert":"integrated development environment ","attributes":{"color":"#ffffff","bold":true}},{"insert":"\n","attributes":{"size":"medium","align":"center"}},{"insert":"(IDE)","attributes":{"color":"#ffffff","bold":true}},{"insert":"\n","attributes":{"size":"large","align":"center"}}]}},"rType":"richtext","hali":"","vali":"middle"},"back":{"selectedKey":"fill","fill":{"opac":0.15,"rgb":"#2b2b2a"},"txt":{"rType":"richtext","val":{"ops":[{"insert":"A bundle of tools for coding including a source code editor, build automation tools, and a debugger.","attributes":{"background":"transparent","color":"#cccccc"}},{"insert":"\n","attributes":{"align":"center"}}]}},"rType":"richtext","paddV1":0,"vali":"middle","hali":""}}},"uQH34Fqb1":{"id":"uQH34Fqb1","type":"interactive","subtype":"interactiveCard","setup":{"animation":{"selectedKey":"up"},"front":{"selectedKey":"fill","fill":{"opac":1,"rgb":"#2b2b2a"},"txt":{"rType":"richtext","val":{"ops":[{"attributes":{"color":"#ffffff","bold":true},"insert":"code (v.)"},{"attributes":{"size":"large","align":"center"},"insert":"\n"}]}},"rType":"richtext","hali":"","vali":"middle"},"back":{"selectedKey":"fill","fill":{"opac":1,"rgb":"#2b2b2a"},"txt":{"rType":"richtext","val":{"ops":[{"insert":"v. The act of writing instructions for a computer to carry out.","attributes":{"color":"#cccccc"}},{"insert":"\n","attributes":{"align":"center"}}]}},"rType":"richtext","paddV1":0,"vali":"middle","hali":""}}},"muJ4umTKAN":{"id":"muJ4umTKAN","type":"interactive","subtype":"interactiveLink","setup":{"link":{"selectedKey":"external","external":{"val":"http://catb.org/~esr/jargon/"}},"bg":{"selectedKey":"fill","fill":{"opac":1,"rgb":"#2b2b2a"}},"title":{"rType":"text","val":"The Jargon File"}}},"X9q621uYnV":{"id":"X9q621uYnV","type":"interactive","subtype":"interactiveCard","setup":{"animation":{"selectedKey":"up"},"front":{"selectedKey":"fill","fill":{"opac":1,"rgb":"#2b2b2a"},"txt":{"rType":"richtext","val":{"ops":[{"attributes":{"color":"#ffffff","bold":true},"insert":"Python Shell"},{"attributes":{"size":"large","align":"center"},"insert":"\n"}]}},"rType":"richtext","hali":"","vali":"middle"},"back":{"selectedKey":"fill","fill":{"opac":0.15,"rgb":"#707070"},"txt":{"rType":"richtext","val":{"ops":[{"insert":"The Python shell is an interpreter","attributes":{"color":"#ffffff"}},{"insert":"—","attributes":{"color":"#cccccc"}},{"insert":"a program that reads and executes Python programs line by line.","attributes":{"color":"#ffffff"}},{"insert":"\n","attributes":{"align":"center"}}]}},"rType":"richtext","paddV1":0,"vali":"middle","hali":""}}},"7VYkbljaML":{"id":"7VYkbljaML","type":"interactive","subtype":"interactiveCard","setup":{"animation":{"selectedKey":"up"},"front":{"selectedKey":"fill","fill":{"opac":1,"rgb":"#cebc0b"},"txt":{"rType":"richtext","val":{"ops":[{"insert":"command","attributes":{"color":"#ffffff","bold":true}},{"insert":"\n","attributes":{"size":"large","align":"center"}}]}},"rType":"richtext","hali":"","vali":"middle"},"back":{"selectedKey":"fill","fill":{"opac":0.15,"rgb":"#2b2b2a"},"txt":{"rType":"richtext","val":{"ops":[{"insert":"An instruction or signal that causes a computer to perform one of its basic functions.","attributes":{"color":"#cccccc"}},{"insert":"\n","attributes":{"align":"center"}}]}},"rType":"richtext","paddV1":0,"vali":"middle","hali":""}}},"9CSAV3GcJK":{"id":"9CSAV3GcJK","type":"interactive","subtype":"interactiveCard","setup":{"animation":{"selectedKey":"up"},"front":{"selectedKey":"fill","fill":{"opac":1,"rgb":"#2b2b2a"},"txt":{"rType":"richtext","val":{"ops":[{"attributes":{"color":"#ffffff","bold":true},"insert":"prompt"},{"attributes":{"size":"large","align":"center"},"insert":"\n"}]}},"rType":"richtext","hali":"","vali":"middle"},"back":{"selectedKey":"fill","fill":{"opac":0.3,"rgb":"#707070"},"txt":{"rType":"richtext","val":{"ops":[{"insert":"Symbols within the CLI that show that the computer is ready for the user to input the next command.","attributes":{"color":"#cccccc"}},{"insert":"\n","attributes":{"align":"center"}}]}},"rType":"richtext","paddV1":0,"vali":"middle","hali":""}}},"SabTayEiw":{"id":"SabTayEiw","type":"slide","setup":{"bord":{"size":0,"rad":0},"presenter":{"audio":{"selectedKey":"file","file":{}}},"bg":{"selectedKey":"image","fill":{"opac":1,"rgb":"#FFF"},"img":{"filt":{"opac":100,"gray":0,"blur":0,"tint":{"rgb":"#FFF","opac":0}},"pos":{"type":"crop","fit":{"bg":{"color":{"rgb":"#FFF","opac":100}},"vali":"center","hali":"center"},"crop":{"poi":{"x":517.5,"y":337.5}}},"measures":{"size":{"width":1200,"height":675}},"orig":{"rType":"asset","rSubType":"image","fileName":"mc-abc71677f773083945c147e27b78f690.jpg","fileSize":118382,"val":"mc-abc71677f773083945c147e27b78f690.jpg","aid":"Eu7BzhihS6"}}},"transparentBg":{"selectedKey":false}}},"vI5DjNqjmL":{"id":"vI5DjNqjmL","type":"interactive","subtype":"interactiveCard","setup":{"animation":{"selectedKey":"up"},"front":{"selectedKey":"fill","fill":{"opac":1,"rgb":"#cebc0b"},"txt":{"rType":"richtext","val":{"ops":[{"attributes":{"color":"#ffffff","bold":true},"insert":"program (n.)"},{"attributes":{"size":"large","align":"center"},"insert":"\n"}]}},"rType":"richtext","hali":"","vali":"middle"},"back":{"selectedKey":"fill","fill":{"opac":0.3,"rgb":"#2b2b2a"},"txt":{"rType":"richtext","val":{"ops":[{"insert":"n. An organized collection of instructions that performs a specific task or function when executed.","attributes":{"color":"#cccccc"}},{"insert":"\n","attributes":{"align":"center"}}]}},"rType":"richtext","paddV1":0,"vali":"middle","hali":""}}}},"v":"1"}